{
  "restaurants": [
    {
      "id": 1,
      "name": "Komagene",
      "slogan": "Bana gene sana gene Komagene!",
      "location": "Ümraniye/İSTANBUL",
      "openTime": "08.00",
      "closeTime": "23.00"
    },
    {
      "id": 2,
      "name": "Çiğköfteci Ömer Usta",
      "slogan": "Dünyayı saran lezzet!",
      "location": "Çekmeköy/İSTANBUL",
      "openTime": "10.00",
      "closeTime": "23.00"
    },
    {
      "id": 3,
      "name": "Kral Çiğköfte",
      "slogan": "Çiğköfte lezzetini bizimle yaşayın!",
      "location": "Çekmeköy/İSTANBUL",
      "openTime": "11.00",
      "closeTime": "22.00"
    },
    {
      "id": 4,
      "name": "Oses Çiğköfte",
      "slogan": "Oses olsa da yesek!",
      "location": "Üsküdar/İSTANBUL",
      "openTime": "08.00",
      "closeTime": "23.00"
    },
    {
      "id": 5,
      "name": "Çiğköftem",
      "slogan": "En tatlı acı!",
      "location": "Ataşehir/İSTANBUL",
      "openTime": "06.00",
      "closeTime": "23.59"
    }
  ],
  "reviews": [
    {
      "id": 1,
      "restaurant_id": 1,
      "content": "Sipariş çok hızlı geldi."
    },
    {
      "id": 2,
      "restaurant_id": 1,
      "content": "Açlık komasındaydım, komagene yedim ve kurtuldum."
    },
    {
      "id": 3,
      "restaurant_id": 2,
      "content": "Böyle bir lezzet evrende başka yerde yoktur."
    },
    {
      "id": 4,
      "restaurant_id": 2,
      "content": "Astronot olsam uzaya giderken yanıma bundan alırdım."
    },
    {
      "id": 5,
      "restaurant_id": 3,
      "content": "Kral tacı diye içine taş koymuşlar sanırım..."
    },
    {
      "id": 6,
      "restaurant_id": 3,
      "content": "İdare eder."
    },
    {
      "id": 7,
      "restaurant_id": 4,
      "content": "Bir daha söylemem, söyletmem.."
    },
    {
      "id": 8,
      "restaurant_id": 4,
      "content": "Çok baharatlıydı."
    },
    {
      "id": 9,
      "restaurant_id": 5,
      "content": "Acı seven biri olarak, acısı yerindeydi."
    },
    {
      "id": 10,
      "restaurant_id": 5,
      "content": "Acısı muazzamdı, sayesinde kendimi Adana'da gibi hissettim."
    }
  ]
}